DatastreamNavigator/AppIcon.ico
DatastreamNavigator/DSNavigatorObjectBase.py
DatastreamNavigator/DSNavigator_App.py
DatastreamNavigator/DSNavigator_Frame.py
DatastreamNavigator/DSNavigator_Parser.py
DatastreamNavigator/DatastreamNavigator.py
DatastreamNavigator/__init__.py
DatastreamNavigator-1.0.7.dist-info/METADATA
DatastreamNavigator-1.0.7.dist-info/WHEEL
DatastreamNavigator-1.0.7.dist-info/top_level.txt
DatastreamNavigator-1.0.7.dist-info/RECORD
