Metadata-Version: 2.1
Name: DatastreamNavigator
Version: 1.0.7
Summary: Python package for Datastream Web Services Navigator component
Author: London Stock Exchange
Author-email: datastream@lseg.com
License: Apache Software License (http://www.apache.org/licenses/LICENSE-2.0)
Requires-Python: >=3
Requires-Dist: pandas
Requires-Dist: requests
